web3node/__init__.py
web3node/darwin.py
web3node/gnu.py
web3node/task.py
web3node/win32.py
web3node-0.1.3.dist-info/LICENSE
web3node-0.1.3.dist-info/METADATA
web3node-0.1.3.dist-info/WHEEL
web3node-0.1.3.dist-info/top_level.txt
web3node-0.1.3.dist-info/RECORD
