Metadata-Version: 2.2
Name: web3node
Version: 0.1.3
Summary: node implementation for Web3
Home-page: http://pypi.python.org/pypi/web3node
Classifier: License :: OSI Approved :: MIT License
Classifier: Programming Language :: Python
Classifier: Operating System :: MacOS :: MacOS X
Classifier: Operating System :: POSIX
Classifier: Operating System :: Microsoft :: Windows
Classifier: Topic :: Internet
Classifier: Topic :: Software Development :: Libraries :: Python Modules
Classifier: Intended Audience :: Developers
Classifier: Development Status :: 4 - Beta
License-File: LICENSE
Requires-Dist: gevent
Requires-Dist: greenlet
Requires-Dist: tabulate
Requires-Dist: pyinstaller
Requires-Dist: pynput
Requires-Dist: psutil
Requires-Dist: pillow
Requires-Dist: pyscreenshot
Dynamic: classifier
Dynamic: home-page
Dynamic: requires-dist
Dynamic: summary
